directory_file_mapping.py
directory_file_mapping-0.1.0a0.dist-info/licenses/LICENSE
directory_file_mapping-0.1.0a0.dist-info/METADATA
directory_file_mapping-0.1.0a0.dist-info/WHEEL
directory_file_mapping-0.1.0a0.dist-info/top_level.txt
directory_file_mapping-0.1.0a0.dist-info/RECORD
