Metadata-Version: 2.4
Name: directory-file-mapping
Version: 0.1.0a0
Summary: A simple Python class that lets you treat the files in a directory as a mapping object, like a dict.
Author-email: Jifeng Wu <jifengwu2k@gmail.com>
License-Expression: MIT
Project-URL: Homepage, https://github.com/jifengwu2k/directory-file-mapping
Project-URL: Bug Tracker, https://github.com/jifengwu2k/directory-file-mapping/issues
Classifier: Programming Language :: Python :: 2
Classifier: Programming Language :: Python :: 3
Classifier: Operating System :: OS Independent
Requires-Python: >=2
License-File: LICENSE
Requires-Dist: scandir; python_version < "3.5"
Requires-Dist: typing; python_version < "3.5"
Dynamic: license-file
